totorials/totorial_17_Blackboxes_with_Verilog_in_a_Resource_File/up_counter.v

module up_counter(
  input         clock,
  input         reset,
  input         io_en,
  input  [31:0] io_count_max,
  output        io_clr,
  output [31:0] io_count
);
  reg [31:0] _RAND_0;
  reg [31:0] countReg; // @[up_counter.scala 16:25]
  wire [31:0] _T_1 = countReg + 32'h1; // @[up_counter.scala 25:26]
  assign io_clr = io_en & io_count == io_count_max; // @[up_counter.scala 29:20]
  assign io_count = countReg; // @[up_counter.scala 28:12]
  always @(posedge clock) begin
    if (reset) begin // @[up_counter.scala 16:25]
      countReg <= 32'h0; // @[up_counter.scala 16:25]
    end else if (io_clr) begin // @[up_counter.scala 22:16]
      countReg <= 32'h0; // @[up_counter.scala 23:14]
    end else if (io_en) begin // @[up_counter.scala 24:21]
      countReg <= _T_1; // @[up_counter.scala 25:14]
    end
  end
endmodule

totorials/totorial_18_Blackboxes_verilog_file_to_clock/tested/clock.v
module clock(
  input         clock,
  input         reset,
  input         io_clock,
  input         io_reset,
  input         io_en,
  input  [31:0] io_count_max,
  input  [31:0] io_count_max_hrs,
  output        io_clr_sec,
  output [31:0] io_count_sec,
  output        io_clr_min,
  output [31:0] io_count_min,
  output        io_clr_hrs,
  output [31:0] io_count_hrs
);
  wire  up_counter_sec_clock; // @[up_counter_clock.scala 27:30]
  wire  up_counter_sec_reset; // @[up_counter_clock.scala 27:30]
  wire  up_counter_sec_io_en; // @[up_counter_clock.scala 27:30]
  wire [31:0] up_counter_sec_io_count_max; // @[up_counter_clock.scala 27:30]
  wire  up_counter_sec_io_clr; // @[up_counter_clock.scala 27:30]
  wire [31:0] up_counter_sec_io_count; // @[up_counter_clock.scala 27:30]
  wire  up_counter_min_clock; // @[up_counter_clock.scala 36:30]
  wire  up_counter_min_reset; // @[up_counter_clock.scala 36:30]
  wire  up_counter_min_io_en; // @[up_counter_clock.scala 36:30]
  wire [31:0] up_counter_min_io_count_max; // @[up_counter_clock.scala 36:30]
  wire  up_counter_min_io_clr; // @[up_counter_clock.scala 36:30]
  wire [31:0] up_counter_min_io_count; // @[up_counter_clock.scala 36:30]
  wire  up_counter_hrs_clock; // @[up_counter_clock.scala 45:30]
  wire  up_counter_hrs_reset; // @[up_counter_clock.scala 45:30]
  wire  up_counter_hrs_io_en; // @[up_counter_clock.scala 45:30]
  wire [31:0] up_counter_hrs_io_count_max; // @[up_counter_clock.scala 45:30]
  wire  up_counter_hrs_io_clr; // @[up_counter_clock.scala 45:30]
  wire [31:0] up_counter_hrs_io_count; // @[up_counter_clock.scala 45:30]
  up_counter up_counter_sec ( // @[up_counter_clock.scala 27:30]
    .clock(up_counter_sec_clock),
    .reset(up_counter_sec_reset),
    .io_en(up_counter_sec_io_en),
    .io_count_max(up_counter_sec_io_count_max),
    .io_clr(up_counter_sec_io_clr),
    .io_count(up_counter_sec_io_count)
  );
  up_counter up_counter_min ( // @[up_counter_clock.scala 36:30]
    .clock(up_counter_min_clock),
    .reset(up_counter_min_reset),
    .io_en(up_counter_min_io_en),
    .io_count_max(up_counter_min_io_count_max),
    .io_clr(up_counter_min_io_clr),
    .io_count(up_counter_min_io_count)
  );
  up_counter up_counter_hrs ( // @[up_counter_clock.scala 45:30]
    .clock(up_counter_hrs_clock),
    .reset(up_counter_hrs_reset),
    .io_en(up_counter_hrs_io_en),
    .io_count_max(up_counter_hrs_io_count_max),
    .io_clr(up_counter_hrs_io_clr),
    .io_count(up_counter_hrs_io_count)
  );
  assign io_clr_sec = up_counter_sec_io_clr; // @[up_counter_clock.scala 32:14]
  assign io_count_sec = up_counter_sec_io_count; // @[up_counter_clock.scala 33:16]
  assign io_clr_min = up_counter_min_io_clr; // @[up_counter_clock.scala 41:14]
  assign io_count_min = up_counter_min_io_count; // @[up_counter_clock.scala 42:16]
  assign io_clr_hrs = up_counter_hrs_io_clr; // @[up_counter_clock.scala 50:14]
  assign io_count_hrs = up_counter_hrs_io_count; // @[up_counter_clock.scala 51:16]
  assign up_counter_sec_clock = io_clock; // @[up_counter_clock.scala 28:27]
  assign up_counter_sec_reset = io_reset; // @[up_counter_clock.scala 29:27]
  assign up_counter_sec_io_en = io_en; // @[up_counter_clock.scala 30:28]
  assign up_counter_sec_io_count_max = io_count_max; // @[up_counter_clock.scala 31:34]
  assign up_counter_min_clock = io_clock; // @[up_counter_clock.scala 37:27]
  assign up_counter_min_reset = io_reset; // @[up_counter_clock.scala 38:27]
  assign up_counter_min_io_en = io_clr_sec; // @[up_counter_clock.scala 39:28]
  assign up_counter_min_io_count_max = io_count_max; // @[up_counter_clock.scala 40:34]
  assign up_counter_hrs_clock = io_clock; // @[up_counter_clock.scala 46:27]
  assign up_counter_hrs_reset = io_reset; // @[up_counter_clock.scala 47:27]
  assign up_counter_hrs_io_en = io_clr_min; // @[up_counter_clock.scala 48:28]
  assign up_counter_hrs_io_count_max = io_count_max_hrs; // @[up_counter_clock.scala 49:34]
endmodule

totorials/totorial_18_Blackboxes_verilog_file_to_clock/tested/tb_clock.v
module tb_clock;


reg			        clock;
reg 		        reset;
reg				    en;
reg	    [31:0]	    count_max;

reg	    [31:0]	    count_max_hrs;


wire                clr_sec;
wire    [31:0]	    count_sec;

wire                clr_min;
wire    [31:0]      count_min;

wire                clr_hrs;
wire    [31:0]      count_hrs;





clock

clock_inst(
.io_clock            (clock        ),
.io_reset            (reset        ),
.io_en            (en              ),
.io_count_max     (count_max       ),

.io_count_max_hrs (count_max_hrs  ),

.io_clr_sec       (clr_sec         ),
.io_count_sec     (count_sec       ),

.io_clr_min       (clr_min         ),
.io_count_min     (count_min       ),

.io_clr_hrs       (clr_hrs         ),
.io_count_hrs     (count_hrs       )


);

initial
begin
clock = 0;
forever
#5 clock = ~clock;
end


initial 
begin

    $dumpfile("wave.vcd");
	$dumpvars(0, tb_clock);
	
reset     = 0;
en        = 0;	
count_max = 32'd59;
count_max_hrs = 32'd23;

@(posedge clock)
reset <= #1 1;
@(posedge clock)
reset <= #1 0;

@(posedge clock);
#1 en = 1;

repeat(7200) @(posedge clock);
#1 en = 0;

repeat(20)@(posedge clock);
$finish;
   
	
end

endmodule

totorials/totorial_18_Blackboxes_verilog_file_to_clock/tested/wave.vcd
$date
	Mon Mar 06 16:13:16 2023
$end
$version
	Icarus Verilog
$end
$timescale
	1s
$end
$scope module tb_clock $end
$var wire 1 ! clr_hrs $end
$var wire 1 " clr_min $end
$var wire 1 # clr_sec $end
$var wire 32 $ count_hrs [31:0] $end
$var wire 32 % count_min [31:0] $end
$var wire 32 & count_sec [31:0] $end
$var reg 1 ' clock $end
$var reg 32 ( count_max [31:0] $end
$var reg 32 ) count_max_hrs [31:0] $end
$var reg 1 * en $end
$var reg 1 + reset $end
$scope module clock_inst $end
$var wire 1 , clock $end
$var wire 1 - io_clock $end
$var wire 1 ! io_clr_hrs $end
$var wire 1 " io_clr_min $end
$var wire 1 # io_clr_sec $end
$var wire 32 . io_count_hrs [31:0] $end
$var wire 32 / io_count_max [31:0] $end
$var wire 32 0 io_count_max_hrs [31:0] $end
$var wire 32 1 io_count_min [31:0] $end
$var wire 32 2 io_count_sec [31:0] $end
$var wire 1 3 io_en $end
$var wire 1 4 io_reset $end
$var wire 1 5 reset $end
$var wire 1 6 up_counter_hrs_clock $end
$var wire 1 7 up_counter_hrs_io_clr $end
$var wire 32 8 up_counter_hrs_io_count [31:0] $end
$var wire 32 9 up_counter_hrs_io_count_max [31:0] $end
$var wire 1 : up_counter_hrs_io_en $end
$var wire 1 ; up_counter_hrs_reset $end
$var wire 1 < up_counter_min_clock $end
$var wire 1 = up_counter_min_io_clr $end
$var wire 32 > up_counter_min_io_count [31:0] $end
$var wire 32 ? up_counter_min_io_count_max [31:0] $end
$var wire 1 @ up_counter_min_io_en $end
$var wire 1 A up_counter_min_reset $end
$var wire 1 B up_counter_sec_clock $end
$var wire 1 C up_counter_sec_io_clr $end
$var wire 32 D up_counter_sec_io_count [31:0] $end
$var wire 32 E up_counter_sec_io_count_max [31:0] $end
$var wire 1 F up_counter_sec_io_en $end
$var wire 1 G up_counter_sec_reset $end
$scope module up_counter_sec $end
$var wire 32 H _T_1 [31:0] $end
$var wire 1 B clock $end
$var wire 1 C io_clr $end
$var wire 32 I io_count [31:0] $end
$var wire 32 J io_count_max [31:0] $end
$var wire 1 F io_en $end
$var wire 1 G reset $end
$var reg 32 K countReg [31:0] $end
$upscope $end
$scope module up_counter_min $end
$var wire 32 L _T_1 [31:0] $end
$var wire 1 < clock $end
$var wire 1 = io_clr $end
$var wire 32 M io_count [31:0] $end
$var wire 32 N io_count_max [31:0] $end
$var wire 1 @ io_en $end
$var wire 1 A reset $end
$var reg 32 O countReg [31:0] $end
$upscope $end
$scope module up_counter_hrs $end
$var wire 32 P _T_1 [31:0] $end
$var wire 1 6 clock $end
$var wire 1 7 io_clr $end
$var wire 32 Q io_count [31:0] $end
$var wire 32 R io_count_max [31:0] $end
$var wire 1 : io_en $end
$var wire 1 ; reset $end
$var reg 32 S countReg [31:0] $end
$upscope $end
$upscope $end
$upscope $end
$enddefinitions $end
#0
$dumpvars
bx S
b10111 R
bx Q
bx P
bx O
b111011 N
bx M
bx L
bx K
b111011 J
bx I
bx H
0G
0F
b111011 E
bx D
0C
0B
0A
0@
b111011 ?
bx >
0=
0<
0;
0:
b10111 9
bx 8
07
06
z5
04
03
bx 2
bx 1
b10111 0
b111011 /
bx .
0-
z,
0+
0*
b10111 )
b111011 (
0'
bx &
bx %
bx $
0#
0"
0!
$end
#5
1'
1B
1<
16
1-
#6
1+
1G
1A
1;
14
#10
0'
0B
0<
06
0-
#15
b0 K
b1 H
b0 D
b0 I
b0 &
b0 2
b0 O
b1 L
b0 >
b0 M
b0 %
b0 1
b0 S
b1 P
b0 8
b0 Q
b0 $
b0 .
1'
1B
1<
16
1-
#16
0+
0G
0A
0;
04
#20
0'
0B
0<
06
0-
#25
1'
1B
1<
16
1-
#26
1*
1F
13
#30
0'
0B
0<
06
0-
#35
b1 K
b10 H
b1 D
b1 I
b1 &
b1 2
1'
1B
1<
16
1-
#40
0'
0B
0<
06
0-
#45
b10 K
b11 H
b10 D
b10 I
b10 &
b10 2
1'
1B
1<
16
1-
#50
0'
0B
0<
06
0-
#55
b11 K
b100 H
b11 D
b11 I
b11 &
b11 2
1'
1B
1<
16
1-
#60
0'
0B
0<
06
0-
#65
b100 K
b101 H
b100 D
b100 I
b100 &
b100 2
1'
1B
1<
16
1-
#70
0'
0B
0<
06
0-
#75
b101 K
b110 H
b101 D
b101 I
b101 &
b101 2
1'
1B
1<
16
1-
#80
0'
0B
0<
06
0-
#85
b110 K
b111 H
b110 D
b110 I
b110 &
b110 2
1'
1B
1<
16
1-
#90
0'
0B
0<
06
0-
#95
b111 K
b1000 H
b111 D
b111 I
b111 &
b111 2
1'
1B
1<
16
1-
#100
0'
0B
0<
06
0-
#105
b1000 K
b1001 H
b1000 D
b1000 I
b1000 &
b1000 2
1'
1B
1<
16
1-
#110
0'
0B
0<
06
0-
#115
b1001 K
b1010 H
b1001 D
b1001 I
b1001 &
b1001 2
1'
1B
1<
16
1-
#120
0'
0B
0<
06
0-
#125
b1010 K
b1011 H
b1010 D
b1010 I
b1010 &
b1010 2
1'
1B
1<
16
1-
#130
0'
0B
0<
06
0-
#135
b1011 K
b1100 H
b1011 D
b1011 I
b1011 &
b1011 2
1'
1B
1<
16
1-
#140
0'
0B
0<
06
0-
#145
b1100 K
b1101 H
b1100 D
b1100 I
b1100 &
b1100 2
1'
1B
1<
16
1-
#150
0'
0B
0<
06
0-
#155
b1101 K
b1110 H
b1101 D
b1101 I
b1101 &
b1101 2
1'
1B
1<
16
1-
#160
0'
0B
0<
06
0-
#165
b1110 K
b1111 H
b1110 D
b1110 I
b1110 &
b1110 2
1'
1B
1<
16
1-
#170
0'
0B
0<
06
0-
#175
b1111 K
b10000 H
b1111 D
b1111 I
b1111 &
b1111 2
1'
1B
1<
16
1-
#180
0'
0B
0<
06
0-
#185
b10000 K
b10001 H
b10000 D
b10000 I
b10000 &
b10000 2
1'
1B
1<
16
1-
#190
0'
0B
0<
06
0-
#195
b10001 K
b10010 H
b10001 D
b10001 I
b10001 &
b10001 2
1'
1B
1<
16
1-
#200
0'
0B
0<
06
0-
#205
b10010 K
b10011 H
b10010 D
b10010 I
b10010 &
b10010 2
1'
1B
1<
16
1-
#210
0'
0B
0<
06
0-
#215
b10011 K
b10100 H
b10011 D
b10011 I
b10011 &
b10011 2
1'
1B
1<
16
1-
#220
0'
0B
0<
06
0-
#225
b10100 K
b10101 H
b10100 D
b10100 I
b10100 &
b10100 2
1'
1B
1<
16
1-
#230
0'
0B
0<
06
0-
#235
b10101 K
b10110 H
b10101 D
b10101 I
b10101 &
b10101 2
1'
1B
1<
16
1-
#240
0'
0B
0<
06
0-
#245
b10110 K
b10111 H
b10110 D
b10110 I
b10110 &
b10110 2
1'
1B
1<
16
1-
#250
0'
0B
0<
06
0-
#255
b10111 K
b11000 H
b10111 D
b10111 I
b10111 &
b10111 2
1'
1B
1<
16
1-
#260
0'
0B
0<
06
0-
#265
b11000 K
b11001 H
b11000 D
b11000 I
b11000 &
b11000 2
1'
1B
1<
16
1-
#270
0'
0B
0<
06
0-
#275
b11001 K
b11010 H
b11001 D
b11001 I
b11001 &
b11001 2
1'
1B
1<
16
1-
#280
0'
0B
0<
06
0-
#285
b11010 K
b11011 H
b11010 D
b11010 I
b11010 &
b11010 2
1'
1B
1<
16
1-
#290
0'
0B
0<
06
0-
#295
b11011 K
b11100 H
b11011 D
b11011 I
b11011 &
b11011 2
1'
1B
1<
16
1-
#300
0'
0B
0<
06
0-
#305
b11100 K
b11101 H
b11100 D
b11100 I
b11100 &
b11100 2
1'
1B
1<
16
1-
#310
0'
0B
0<
06
0-
#315
b11101 K
b11110 H
b11101 D
b11101 I
b11101 &
b11101 2
1'
1B
1<
16
1-
#320
0'
0B
0<
06
0-
#325
b11110 K
b11111 H
b11110 D
b11110 I
b11110 &
b11110 2
1'
1B
1<
16
1-
#330
0'
0B
0<
06
0-
#335
b11111 K
b100000 H
b11111 D
b11111 I
b11111 &
b11111 2
1'
1B
1<
16
1-
#340
0'
0B
0<
06
0-
#345
b100000 K
b100001 H
b100000 D
b100000 I
b100000 &
b100000 2
1'
1B
1<
16
1-
#350
0'
0B
0<
06
0-
#355
b100001 K
b100010 H
b100001 D
b100001 I
b100001 &
b100001 2
1'
1B
1<
16
1-
#360
0'
0B
0<
06
0-
#365
b100010 K
b100011 H
b100010 D
b100010 I
b100010 &
b100010 2
1'
1B
1<
16
1-
#370
0'
0B
0<
06
0-
#375
b100011 K
b100100 H
b100011 D
b100011 I
b100011 &
b100011 2
1'
1B
1<
16
1-
#380
0'
0B
0<
06
0-
#385
b100100 K
b100101 H
b100100 D
b100100 I
b100100 &
b100100 2
1'
1B
1<
16
1-
#390
0'
0B
0<
06
0-
#395
b100101 K
b100110 H
b100101 D
b100101 I
b100101 &
b100101 2
1'
1B
1<
16
1-
#400
0'
0B
0<
06
0-
#405
b100110 K
b100111 H
b100110 D
b100110 I
b100110 &
b100110 2
1'
1B
1<
16
1-
#410
0'
0B
0<
06
0-
#415
b100111 K
b101000 H
b100111 D
b100111 I
b100111 &
b100111 2
1'
1B
1<
16
1-
#420
0'
0B
0<
06
0-
#425
b101000 K
b101001 H
b101000 D
b101000 I
b101000 &
b101000 2
1'
1B
1<
16
1-
#430
0'
0B
0<
06
0-
#435
b101001 K
b101010 H
b101001 D
b101001 I
b101001 &
b101001 2
1'
1B
1<
16
1-
#440
0'
0B
0<
06
0-
#445
b101010 K
b101011 H
b101010 D
b101010 I
b101010 &
b101010 2
1'
1B
1<
16
1-
#450
0'
0B
0<
06
0-
#455
b101011 K
b101100 H
b101011 D
b101011 I
b101011 &
b101011 2
1'
1B
1<
16
1-
#460
0'
0B
0<
06
0-
#465
b101100 K
b101101 H
b101100 D
b101100 I
b101100 &
b101100 2
1'
1B
1<
16
1-
#470
0'
0B
0<
06
0-
#475
b101101 K
b101110 H
b101101 D
b101101 I
b101101 &
b101101 2
1'
1B
1<
16
1-
#480
0'
0B
0<
06
0-
#485
b101110 K
b101111 H
b101110 D
b101110 I
b101110 &
b101110 2
1'
1B
1<
16
1-
#490
0'
0B
0<
06
0-
#495
b101111 K
b110000 H
b101111 D
b101111 I
b101111 &
b101111 2
1'
1B
1<
16
1-
#500
0'
0B
0<
06
0-
#505
b110000 K
b110001 H
b110000 D
b110000 I
b110000 &
b110000 2
1'
1B
1<
16
1-
#510
0'
0B
0<
06
0-
#515
b110001 K
b110010 H
b110001 D
b110001 I
b110001 &
b110001 2
1'
1B
1<
16
1-
#520
0'
0B
0<
06
0-
#525
b110010 K
b110011 H
b110010 D
b110010 I
b110010 &
b110010 2
1'
1B
1<
16
1-
#530
0'
0B
0<
06
0-
#535
b110011 K
b110100 H
b110011 D
b110011 I
b110011 &
b110011 2
1'
1B
1<
16
1-
#540
0'
0B
0<
06
0-
#545
b110100 K
b110101 H
b110100 D
b110100 I
b110100 &
b110100 2
1'
1B
1<
16
1-
#550
0'
0B
0<
06
0-
#555
b110101 K
b110110 H
b110101 D
b110101 I
b110101 &
b110101 2
1'
1B
1<
16
1-
#560
0'
0B
0<
06
0-
#565
b110110 K
b110111 H
b110110 D
b110110 I
b110110 &
b110110 2
1'
1B
1<
16
1-
#570
0'
0B
0<
06
0-
#575
b110111 K
b111000 H
b110111 D
b110111 I
b110111 &
b110111 2
1'
1B
1<
16
1-
#580
0'
0B
0<
06
0-
#585
b111000 K
b111001 H
b111000 D
b111000 I
b111000 &
b111000 2
1'
1B
1<
16
1-
#590
0'
0B
0<
06
0-
#595
b111001 K
b111010 H
b111001 D
b111001 I
b111001 &
b111001 2
1'
1B
1<
16
1-
#600
0'
0B
0<
06
0-
#605
b111010 K
b111011 H
b111010 D
b111010 I
b111010 &
b111010 2
1'
1B
1<
16
1-
#610
0'
0B
0<
06
0-
#615
1C
1@
1#
b111011 K
b111100 H
b111011 D
b111011 I
b111011 &
b111011 2
1'
1B
1<
16
1-
#620
0'
0B
0<
06
0-
#625
0C
0@
0#
b0 K
b1 H
b0 D
b0 I
b0 &
b0 2
b1 O
b10 L
b1 >
b1 M
b1 %
b1 1
1'
1B
1<
16
1-
#630
0'
0B
0<
06
0-
#635
b1 K
b10 H
b1 D
b1 I
b1 &
b1 2
1'
1B
1<
16
1-
#640
0'
0B
0<
06
0-
#645
b10 K
b11 H
b10 D
b10 I
b10 &
b10 2
1'
1B
1<
16
1-
#650
0'
0B
0<
06
0-
#655
b11 K
b100 H
b11 D
b11 I
b11 &
b11 2
1'
1B
1<
16
1-
#660
0'
0B
0<
06
0-
#665
b100 K
b101 H
b100 D
b100 I
b100 &
b100 2
1'
1B
1<
16
1-
#670
0'
0B
0<
06
0-
#675
b101 K
b110 H
b101 D
b101 I
b101 &
b101 2
1'
1B
1<
16
1-
#680
0'
0B
0<
06
0-
#685
b110 K
b111 H
b110 D
b110 I
b110 &
b110 2
1'
1B
1<
16
1-
#690
0'
0B
0<
06
0-
#695
b111 K
b1000 H
b111 D
b111 I
b111 &
b111 2
1'
1B
1<
16
1-
#700
0'
0B
0<
06
0-
#705
b1000 K
b1001 H
b1000 D
b1000 I
b1000 &
b1000 2
1'
1B
1<
16
1-
#710
0'
0B
0<
06
0-
#715
b1001 K
b1010 H
b1001 D
b1001 I
b1001 &
b1001 2
1'
1B
1<
16
1-
#720
0'
0B
0<
06
0-
#725
b1010 K
b1011 H
b1010 D
b1010 I
b1010 &
b1010 2
1'
1B
1<
16
1-
#730
0'
0B
0<
06
0-
#735
b1011 K
b1100 H
b1011 D
b1011 I
b1011 &
b1011 2
1'
1B
1<
16
1-
#740
0'
0B
0<
06
0-
#745
b1100 K
b1101 H
b1100 D
b1100 I
b1100 &
b1100 2
1'
1B
1<
16
1-
#750
0'
0B
0<
06
0-
#755
b1101 K
b1110 H
b1101 D
b1101 I
b1101 &
b1101 2
1'
1B
1<
16
1-
#760
0'
0B
0<
06
0-
#765
b1110 K
b1111 H
b1110 D
b1110 I
b1110 &
b1110 2
1'
1B
1<
16
1-
#770
0'
0B
0<
06
0-
#775
b1111 K
b10000 H
b1111 D
b1111 I
b1111 &
b1111 2
1'
1B
1<
16
1-
#780
0'
0B
0<
06
0-
#785
b10000 K
b10001 H
b10000 D
b10000 I
b10000 &
b10000 2
1'
1B
1<
16
1-
#790
0'
0B
0<
06
0-
#795
b10001 K
b10010 H
b10001 D
b10001 I
b10001 &
b10001 2
1'
1B
1<
16
1-
#800
0'
0B
0<
06
0-
#805
b10010 K
b10011 H
b10010 D
b10010 I
b10010 &
b10010 2
1'
1B
1<
16
1-
#810
0'
0B
0<
06
0-
#815
b10011 K
b10100 H
b10011 D
b10011 I
b10011 &
b10011 2
1'
1B
1<
16
1-
#820
0'
0B
0<
06
0-
#825
b10100 K
b10101 H
b10100 D
b10100 I
b10100 &
b10100 2
1'
1B
1<
16
1-
#830
0'
0B
0<
06
0-
#835
b10101 K
b10110 H
b10101 D
b10101 I
b10101 &
b10101 2
1'
1B
1<
16
1-
#840
0'
0B
0<
06
0-
#845
b10110 K
b10111 H
b10110 D
b10110 I
b10110 &
b10110 2
1'
1B
1<
16
1-
#850
0'
0B
0<
06
0-
#855
b10111 K
b11000 H
b10111 D
b10111 I
b10111 &
b10111 2
1'
1B
1<
16
1-
#860
0'
0B
0<
06
0-
#865
b11000 K
b11001 H
b11000 D
b11000 I
b11000 &
b11000 2
1'
1B
1<
16
1-
#870
0'
0B
0<
06
0-
#875
b11001 K
b11010 H
b11001 D
b11001 I
b11001 &
b11001 2
1'
1B
1<
16
1-
#880
0'
0B
0<
06
0-
#885
b11010 K
b11011 H
b11010 D
b11010 I
b11010 &
b11010 2
1'
1B
1<
16
1-
#890
0'
0B
0<
06
0-
#895
b11011 K
b11100 H
b11011 D
b11011 I
b11011 &
b11011 2
1'
1B
1<
16
1-
#900
0'
0B
0<
06
0-
#905
b11100 K
b11101 H
b11100 D
b11100 I
b11100 &
b11100 2
1'
1B
1<
16
1-
#910
0'
0B
0<
06
0-
#915
b11101 K
b11110 H
b11101 D
b11101 I
b11101 &
b11101 2
1'
1B
1<
16
1-
#920
0'
0B
0<
06
0-
#925
b11110 K
b11111 H
b11110 D
b11110 I
b11110 &
b11110 2
1'
1B
1<
16
1-
#930
0'
0B
0<
06
0-
#935
b11111 K
b100000 H
b11111 D
b11111 I
b11111 &
b11111 2
1'
1B
1<
16
1-
#940
0'
0B
0<
06
0-
#945
b100000 K
b100001 H
b100000 D
b100000 I
b100000 &
b100000 2
1'
1B
1<
16
1-
#950
0'
0B
0<
06
0-
#955
b100001 K
b100010 H
b100001 D
b100001 I
b100001 &
b100001 2
1'
1B
1<
16
1-
#960
0'
0B
0<
06
0-
#965
b100010 K
b100011 H
b100010 D
b100010 I
b100010 &
b100010 2
1'
1B
1<
16
1-
#970
0'
0B
0<
06
0-
#975
b100011 K
b100100 H
b100011 D
b100011 I
b100011 &
b100011 2
1'
1B
1<
16
1-
#980
0'
0B
0<
06
0-
#985
b100100 K
b100101 H
b100100 D
b100100 I
b100100 &
b100100 2
1'
1B
1<
16
1-
#990
0'
0B
0<
06
0-
#995
b100101 K
b100110 H
b100101 D
b100101 I
b100101 &
b100101 2
1'
1B
1<
16
1-
#1000
0'
0B
0<
06
0-
#1005
b100110 K
b100111 H
b100110 D
b100110 I
b100110 &
b100110 2
1'
1B
1<
16
1-
#1010
0'
0B
0<
06
0-
#1015
b100111 K
b101000 H
b100111 D
b100111 I
b100111 &
b100111 2
1'
1B
1<
16
1-
#1020
0'
0B
0<
06
0-
#1025
b101000 K
b101001 H
b101000 D
b101000 I
b101000 &
b101000 2
1'
1B
1<
16
1-
#1030
0'
0B
0<
06
0-
#1035
b101001 K
b101010 H
b101001 D
b101001 I
b101001 &
b101001 2
1'
1B
1<
16
1-
#1040
0'
0B
0<
06
0-
#1045
b101010 K
b101011 H
b101010 D
b101010 I
b101010 &
b101010 2
1'
1B
1<
16
1-
#1050
0'
0B
0<
06
0-
#1055
b101011 K
b101100 H
b101011 D
b101011 I
b101011 &
b101011 2
1'
1B
1<
16
1-
#1060
0'
0B
0<
06
0-
#1065
b101100 K
b101101 H
b101100 D
b101100 I
b101100 &
b101100 2
1'
1B
1<
16
1-
#1070
0'
0B
0<
06
0-
#1075
b101101 K
b101110 H
b101101 D
b101101 I
b101101 &
b101101 2
1'
1B
1<
16
1-
#1080
0'
0B
0<
06
0-
#1085
b101110 K
b101111 H
b101110 D
b101110 I
b101110 &
b101110 2
1'
1B
1<
16
1-
#1090
0'
0B
0<
06
0-
#1095
b101111 K
b110000 H
b101111 D
b101111 I
b101111 &
b101111 2
1'
1B
1<
16
1-
#1100
0'
0B
0<
06
0-
#1105
b110000 K
b110001 H
b110000 D
b110000 I
b110000 &
b110000 2
1'
1B
1<
16
1-
#1110
0'
0B
0<
06
0-
#1115
b110001 K
b110010 H
b110001 D
b110001 I
b110001 &
b110001 2
1'
1B
1<
16
1-
#1120
0'
0B
0<
06
0-
#1125
b110010 K
b110011 H
b110010 D
b110010 I
b110010 &
b110010 2
1'
1B
1<
16
1-
#1130
0'
0B
0<
06
0-
#1135
b110011 K
b110100 H
b110011 D
b110011 I
b110011 &
b110011 2
1'
1B
1<
16
1-
#1140
0'
0B
0<
06
0-
#1145
b110100 K
b110101 H
b110100 D
b110100 I
b110100 &
b110100 2
1'
1B
1<
16
1-
#1150
0'
0B
0<
06
0-
#1155
b110101 K
b110110 H
b110101 D
b110101 I
b110101 &
b110101 2
1'
1B
1<
16
1-
#1160
0'
0B
0<
06
0-
#1165
b110110 K
b110111 H
b110110 D
b110110 I
b110110 &
b110110 2
1'
1B
1<
16
1-
#1170
0'
0B
0<
06
0-
#1175
b110111 K
b111000 H
b110111 D
b110111 I
b110111 &
b110111 2
1'
1B
1<
16
1-
#1180
0'
0B
0<
06
0-
#1185
b111000 K
b111001 H
b111000 D
b111000 I
b111000 &
b111000 2
1'
1B
1<
16
1-
#1190
0'
0B
0<
06
0-
#1195
b111001 K
b111010 H
b111001 D
b111001 I
b111001 &
b111001 2
1'
1B
1<
16
1-
#1200
0'
0B
0<
06
0-
#1205
b111010 K
b111011 H
b111010 D
b111010 I
b111010 &
b111010 2
1'
1B
1<
16
1-
#1210
0'
0B
0<
06
0-
#1215
1C
1@
1#
b111011 K
b111100 H
b111011 D
b111011 I
b111011 &
b111011 2
1'
1B
1<
16
1-
#1220
0'
0B
0<
06
0-
#1225
0C
0@
0#
b0 K
b1 H
b0 D
b0 I
b0 &
b0 2
b10 O
b11 L
b10 >
b10 M
b10 %
b10 1
1'
1B
1<
16
1-
#1230
0'
0B
0<
06
0-
#1235
b1 K
b10 H
b1 D
b1 I
b1 &
b1 2
1'
1B
1<
16
1-
#1240
0'
0B
0<
06
0-
#1245
b10 K
b11 H
b10 D
b10 I
b10 &
b10 2
1'
1B
1<
16
1-
#1250
0'
0B
0<
06
0-
#1255
b11 K
b100 H
b11 D
b11 I
b11 &
b11 2
1'
1B
1<
16
1-
#1260
0'
0B
0<
06
0-
#1265
b100 K
b101 H
b100 D
b100 I
b100 &
b100 2
1'
1B
1<
16
1-
#1270
0'
0B
0<
06
0-
#1275
b101 K
b110 H
b101 D
b101 I
b101 &
b101 2
1'
1B
1<
16
1-
#1280
0'
0B
0<
06
0-
#1285
b110 K
b111 H
b110 D
b110 I
b110 &
b110 2
1'
1B
1<
16
1-
#1290
0'
0B
0<
06
0-
#1295
b111 K
b1000 H
b111 D
b111 I
b111 &
b111 2
1'
1B
1<
16
1-
#1300
0'
0B
0<
06
0-
#1305
b1000 K
b1001 H
b1000 D
b1000 I
b1000 &
b1000 2
1'
1B
1<
16
1-
#1310
0'
0B
0<
06
0-
#1315
b1001 K
b1010 H
b1001 D
b1001 I
b1001 &
b1001 2
1'
1B
1<
16
1-
#1320
0'
0B
0<
06
0-
#1325
b1010 K
b1011 H
b1010 D
b1010 I
b1010 &
b1010 2
1'
1B
1<
16
1-
#1330
0'
0B
0<
06
0-
#1335
b1011 K
b1100 H
b1011 D
b1011 I
b1011 &
b1011 2
1'
1B
1<
16
1-
#1340
0'
0B
0<
06
0-
#1345
b1100 K
b1101 H
b1100 D
b1100 I
b1100 &
b1100 2
1'
1B
1<
16
1-
#1350
0'
0B
0<
06
0-
#1355
b1101 K
b1110 H
b1101 D
b1101 I
b1101 &
b1101 2
1'
1B
1<
16
1-
#1360
0'
0B
0<
06
0-
#1365
b1110 K
b1111 H
b1110 D
b1110 I
b1110 &
b1110 2
1'
1B
1<
16
1-
#1370
0'
0B
0<
06
0-
#1375
b1111 K
b10000 H
b1111 D
b1111 I
b1111 &
b1111 2
1'
1B
1<
16
1-
#1380
0'
0B
0<
06
0-
#1385
b10000 K
b10001 H
b10000 D
b10000 I
b10000 &
b10000 2
1'
1B
1<
16
1-
#1390
0'
0B
0<
06
0-
#1395
b10001 K
b10010 H
b10001 D
b10001 I
b10001 &
b10001 2
1'
1B
1<
16
1-
#1400
0'
0B
0<
06
0-
#1405
b10010 K
b10011 H
b10010 D
b10010 I
b10010 &
b10010 2
1'
1B
1<
16
1-
#1410
0'
0B
0<
06
0-
#1415
b10011 K
b10100 H
b10011 D
b10011 I
b10011 &
b10011 2
1'
1B
1<
16
1-
#1420
0'
0B
0<
06
0-
#1425
b10100 K
b10101 H
b10100 D
b10100 I
b10100 &
b10100 2
1'
1B
1<
16
1-
#1430
0'
0B
0<
06
0-
#1435
b10101 K
b10110 H
b10101 D
b10101 I
b10101 &
b10101 2
1'
1B
1<
16
1-
#1440
0'
0B
0<
06
0-
