totorials/totorial_17_Blackboxes_with_Verilog_in_a_Resource_File/up_counter.v

module up_counter(
  input         clock,
  input         reset,
  input         io_en,
  input  [31:0] io_count_max,
  output        io_clr,
  output [31:0] io_count
);
  reg [31:0] _RAND_0;
  reg [31:0] countReg; // @[up_counter.scala 16:25]
  wire [31:0] _T_1 = countReg + 32'h1; // @[up_counter.scala 25:26]
  assign io_clr = io_en & io_count == io_count_max; // @[up_counter.scala 29:20]
  assign io_count = countReg; // @[up_counter.scala 28:12]
  always @(posedge clock) begin
    if (reset) begin // @[up_counter.scala 16:25]
      countReg <= 32'h0; // @[up_counter.scala 16:25]
    end else if (io_clr) begin // @[up_counter.scala 22:16]
      countReg <= 32'h0; // @[up_counter.scala 23:14]
    end else if (io_en) begin // @[up_counter.scala 24:21]
      countReg <= _T_1; // @[up_counter.scala 25:14]
    end
  end
endmodule

totorials/totorial_22_Blackboxes_verilog_file_to_clock/clock.v
module clock(
  input         clock,
  input         reset,
  input         io_clock,
  input         io_reset,
  output [31:0] io_count_sec,
  output [31:0] io_count_min,
  output [31:0] io_count_hrs
);
  wire  up_counter_sec_clock; // @[up_counter_clock.scala 50:30]
  wire  up_counter_sec_reset; // @[up_counter_clock.scala 50:30]
  wire  up_counter_sec_io_en; // @[up_counter_clock.scala 50:30]
  wire [31:0] up_counter_sec_io_count_max; // @[up_counter_clock.scala 50:30]
  wire  up_counter_sec_io_clr; // @[up_counter_clock.scala 50:30]
  wire [31:0] up_counter_sec_io_count; // @[up_counter_clock.scala 50:30]
  wire  up_counter_min_clock; // @[up_counter_clock.scala 59:30]
  wire  up_counter_min_reset; // @[up_counter_clock.scala 59:30]
  wire  up_counter_min_io_en; // @[up_counter_clock.scala 59:30]
  wire [31:0] up_counter_min_io_count_max; // @[up_counter_clock.scala 59:30]
  wire  up_counter_min_io_clr; // @[up_counter_clock.scala 59:30]
  wire [31:0] up_counter_min_io_count; // @[up_counter_clock.scala 59:30]
  wire  up_counter_hrs_clock; // @[up_counter_clock.scala 68:30]
  wire  up_counter_hrs_reset; // @[up_counter_clock.scala 68:30]
  wire  up_counter_hrs_io_en; // @[up_counter_clock.scala 68:30]
  wire [31:0] up_counter_hrs_io_count_max; // @[up_counter_clock.scala 68:30]
  wire  up_counter_hrs_io_clr; // @[up_counter_clock.scala 68:30]
  wire [31:0] up_counter_hrs_io_count; // @[up_counter_clock.scala 68:30]
  up_counter up_counter_sec ( // @[up_counter_clock.scala 50:30]
    .clock(up_counter_sec_clock),
    .reset(up_counter_sec_reset),
    .io_en(up_counter_sec_io_en),
    .io_count_max(up_counter_sec_io_count_max),
    .io_clr(up_counter_sec_io_clr),
    .io_count(up_counter_sec_io_count)
  );
  up_counter up_counter_min ( // @[up_counter_clock.scala 59:30]
    .clock(up_counter_min_clock),
    .reset(up_counter_min_reset),
    .io_en(up_counter_min_io_en),
    .io_count_max(up_counter_min_io_count_max),
    .io_clr(up_counter_min_io_clr),
    .io_count(up_counter_min_io_count)
  );
  up_counter up_counter_hrs ( // @[up_counter_clock.scala 68:30]
    .clock(up_counter_hrs_clock),
    .reset(up_counter_hrs_reset),
    .io_en(up_counter_hrs_io_en),
    .io_count_max(up_counter_hrs_io_count_max),
    .io_clr(up_counter_hrs_io_clr),
    .io_count(up_counter_hrs_io_count)
  );
  assign io_count_sec = up_counter_sec_io_count; // @[up_counter_clock.scala 56:16]
  assign io_count_min = up_counter_min_io_count; // @[up_counter_clock.scala 65:16]
  assign io_count_hrs = up_counter_hrs_io_count; // @[up_counter_clock.scala 74:16]
  assign up_counter_sec_clock = io_clock; // @[up_counter_clock.scala 51:27]
  assign up_counter_sec_reset = io_reset; // @[up_counter_clock.scala 52:27]
  assign up_counter_sec_io_en = 1'h1; // @[up_counter_clock.scala 27:16 up_counter_clock.scala 39:6]
  assign up_counter_sec_io_count_max = 32'h3b; // @[up_counter_clock.scala 29:27 up_counter_clock.scala 40:17]
  assign up_counter_min_clock = io_clock; // @[up_counter_clock.scala 60:27]
  assign up_counter_min_reset = io_reset; // @[up_counter_clock.scala 61:27]
  assign up_counter_min_io_en = up_counter_sec_io_clr; // @[up_counter_clock.scala 32:21 up_counter_clock.scala 55:11]
  assign up_counter_min_io_count_max = 32'h3b; // @[up_counter_clock.scala 30:27 up_counter_clock.scala 41:17]
  assign up_counter_hrs_clock = io_clock; // @[up_counter_clock.scala 69:27]
  assign up_counter_hrs_reset = io_reset; // @[up_counter_clock.scala 70:27]
  assign up_counter_hrs_io_en = up_counter_min_io_clr; // @[up_counter_clock.scala 33:21 up_counter_clock.scala 64:11]
  assign up_counter_hrs_io_count_max = 32'h17; // @[up_counter_clock.scala 31:27 up_counter_clock.scala 42:17]
endmodule

totorials/totorial_22_Blackboxes_verilog_file_to_clock/tested/tb_clock.v
module tb_clock;

reg clk;
reg reset;
wire [31:0] count_sec;
wire [31:0] count_min;
wire [31:0] count_hrs;


clock clock_inst(
.io_clock           (clk            ),
.io_reset           (reset            ),
.io_count_sec       (count_sec         ),
.io_count_min       (count_min         ),
.io_count_hrs       (count_hrs         )
);


initial
begin
clk = 0;
forever
#5 clk = ~clk;
end




initial 
begin

    $dumpfile("wave.vcd");
	$dumpvars(0, tb_clock);
	
reset     = 0;
@(posedge clk)
reset <= #1 1;
@(posedge clk)
reset <= #1 0;

@(posedge clk);


repeat(7200) @(posedge clk);


repeat(20)@(posedge clk);
$finish;
   
	
end

endmodule

totorials/totorial_22_Blackboxes_verilog_file_to_clock/tested/wave.vcd
$date
	Mon Mar 13 15:18:40 2023
$end
$version
	Icarus Verilog
$end
$timescale
	1s
$end
$scope module tb_clock $end
$var wire 32 ! count_hrs [31:0] $end
$var wire 32 " count_min [31:0] $end
$var wire 32 # count_sec [31:0] $end
$var reg 1 $ clk $end
$var reg 1 % reset $end
$scope module clock_inst $end
$var wire 1 & clock $end
$var wire 1 ' io_clock $end
$var wire 32 ( io_count_hrs [31:0] $end
$var wire 32 ) io_count_min [31:0] $end
$var wire 32 * io_count_sec [31:0] $end
$var wire 1 + io_reset $end
$var wire 1 , reset $end
$var wire 1 - up_counter_hrs_clock $end
$var wire 1 . up_counter_hrs_io_clr $end
$var wire 32 / up_counter_hrs_io_count [31:0] $end
$var wire 32 0 up_counter_hrs_io_count_max [31:0] $end
$var wire 1 1 up_counter_hrs_io_en $end
$var wire 1 2 up_counter_hrs_reset $end
$var wire 1 3 up_counter_min_clock $end
$var wire 1 4 up_counter_min_io_clr $end
$var wire 32 5 up_counter_min_io_count [31:0] $end
$var wire 32 6 up_counter_min_io_count_max [31:0] $end
$var wire 1 7 up_counter_min_io_en $end
$var wire 1 8 up_counter_min_reset $end
$var wire 1 9 up_counter_sec_clock $end
$var wire 1 : up_counter_sec_io_clr $end
$var wire 32 ; up_counter_sec_io_count [31:0] $end
$var wire 32 < up_counter_sec_io_count_max [31:0] $end
$var wire 1 = up_counter_sec_io_en $end
$var wire 1 > up_counter_sec_reset $end
$scope module up_counter_sec $end
$var wire 32 ? _T_1 [31:0] $end
$var wire 1 9 clock $end
$var wire 1 : io_clr $end
$var wire 32 @ io_count [31:0] $end
$var wire 32 A io_count_max [31:0] $end
$var wire 1 = io_en $end
$var wire 1 > reset $end
$var reg 32 B countReg [31:0] $end
$upscope $end
$scope module up_counter_min $end
$var wire 32 C _T_1 [31:0] $end
$var wire 1 3 clock $end
$var wire 1 4 io_clr $end
$var wire 32 D io_count [31:0] $end
$var wire 32 E io_count_max [31:0] $end
$var wire 1 7 io_en $end
$var wire 1 8 reset $end
$var reg 32 F countReg [31:0] $end
$upscope $end
$scope module up_counter_hrs $end
$var wire 32 G _T_1 [31:0] $end
$var wire 1 - clock $end
$var wire 1 . io_clr $end
$var wire 32 H io_count [31:0] $end
$var wire 32 I io_count_max [31:0] $end
$var wire 1 1 io_en $end
$var wire 1 2 reset $end
$var reg 32 J countReg [31:0] $end
$upscope $end
$upscope $end
$upscope $end
$enddefinitions $end
#0
$dumpvars
bx J
b10111 I
bx H
bx G
bx F
b111011 E
bx D
bx C
bx B
b111011 A
bx @
bx ?
0>
1=
b111011 <
bx ;
x:
09
08
x7
b111011 6
bx 5
x4
03
02
x1
b10111 0
bx /
x.
0-
z,
0+
bx *
bx )
bx (
0'
z&
0%
0$
bx #
bx "
bx !
$end
#5
1$
19
13
1-
1'
#6
1%
1>
18
12
1+
#10
0$
09
03
0-
0'
#15
0:
07
04
01
0.
b0 B
b1 ?
b0 ;
b0 @
b0 #
b0 *
b0 F
b1 C
b0 5
b0 D
b0 "
b0 )
b0 J
b1 G
b0 /
b0 H
b0 !
b0 (
1$
19
13
1-
1'
#16
0%
0>
08
02
0+
#20
0$
09
03
0-
0'
#25
b1 B
b10 ?
b1 ;
b1 @
b1 #
b1 *
1$
19
13
1-
1'
#30
0$
09
03
0-
0'
#35
b10 B
b11 ?
b10 ;
b10 @
b10 #
b10 *
1$
19
13
1-
1'
#40
0$
09
03
0-
0'
#45
b11 B
b100 ?
b11 ;
b11 @
b11 #
b11 *
1$
19
13
1-
1'
#50
0$
09
03
0-
0'
#55
b100 B
b101 ?
b100 ;
b100 @
b100 #
b100 *
1$
19
13
1-
1'
#60
0$
09
03
0-
0'
#65
b101 B
b110 ?
b101 ;
b101 @
b101 #
b101 *
1$
19
13
1-
1'
#70
0$
09
03
0-
0'
#75
b110 B
b111 ?
b110 ;
b110 @
b110 #
b110 *
1$
19
13
1-
1'
#80
0$
09
03
0-
0'
#85
b111 B
b1000 ?
b111 ;
b111 @
b111 #
b111 *
1$
19
13
1-
1'
#90
0$
09
03
0-
0'
#95
b1000 B
b1001 ?
b1000 ;
b1000 @
b1000 #
b1000 *
1$
19
13
1-
1'
#100
0$
09
03
0-
0'
#105
b1001 B
b1010 ?
b1001 ;
b1001 @
b1001 #
b1001 *
1$
19
13
1-
1'
#110
0$
09
03
0-
0'
#115
b1010 B
b1011 ?
b1010 ;
b1010 @
b1010 #
b1010 *
1$
19
13
1-
1'
#120
0$
09
03
0-
0'
#125
b1011 B
b1100 ?
b1011 ;
b1011 @
b1011 #
b1011 *
1$
19
13
1-
1'
#130
0$
09
03
0-
0'
#135
b1100 B
b1101 ?
b1100 ;
b1100 @
b1100 #
b1100 *
1$
19
13
1-
1'
#140
0$
09
03
0-
0'
#145
b1101 B
b1110 ?
b1101 ;
b1101 @
b1101 #
b1101 *
1$
19
13
1-
1'
#150
0$
09
03
0-
0'
#155
b1110 B
b1111 ?
b1110 ;
b1110 @
b1110 #
b1110 *
1$
19
13
1-
1'
#160
0$
09
03
0-
0'
#165
b1111 B
b10000 ?
b1111 ;
b1111 @
b1111 #
b1111 *
1$
19
13
1-
1'
#170
0$
09
03
0-
0'
#175
b10000 B
b10001 ?
b10000 ;
b10000 @
b10000 #
b10000 *
1$
19
13
1-
1'
#180
0$
09
03
0-
0'
#185
b10001 B
b10010 ?
b10001 ;
b10001 @
b10001 #
b10001 *
1$
19
13
1-
1'
#190
0$
09
03
0-
0'
#195
b10010 B
b10011 ?
b10010 ;
b10010 @
b10010 #
b10010 *
1$
19
13
1-
1'
#200
0$
09
03
0-
0'
#205
b10011 B
b10100 ?
b10011 ;
b10011 @
b10011 #
b10011 *
1$
19
13
1-
1'
#210
0$
09
03
0-
0'
#215
b10100 B
b10101 ?
b10100 ;
b10100 @
b10100 #
b10100 *
1$
19
13
1-
1'
#220
0$
09
03
0-
0'
#225
b10101 B
b10110 ?
b10101 ;
b10101 @
b10101 #
b10101 *
1$
19
13
1-
1'
#230
0$
09
03
0-
0'
#235
b10110 B
b10111 ?
b10110 ;
b10110 @
b10110 #
b10110 *
1$
19
13
1-
1'
#240
0$
09
03
0-
0'
#245
b10111 B
b11000 ?
b10111 ;
b10111 @
b10111 #
b10111 *
1$
19
13
1-
1'
#250
0$
09
03
0-
0'
#255
b11000 B
b11001 ?
b11000 ;
b11000 @
b11000 #
b11000 *
1$
19
13
1-
1'
#260
0$
09
03
0-
0'
#265
b11001 B
b11010 ?
b11001 ;
b11001 @
b11001 #
b11001 *
1$
19
13
1-
1'
#270
0$
09
03
0-
0'
#275
b11010 B
b11011 ?
b11010 ;
b11010 @
b11010 #
b11010 *
1$
19
13
1-
1'
#280
0$
09
03
0-
0'
#285
b11011 B
b11100 ?
b11011 ;
b11011 @
b11011 #
b11011 *
1$
19
13
1-
1'
#290
0$
09
03
0-
0'
#295
b11100 B
b11101 ?
b11100 ;
b11100 @
b11100 #
b11100 *
1$
19
13
1-
1'
#300
0$
09
03
0-
0'
#305
b11101 B
b11110 ?
b11101 ;
b11101 @
b11101 #
b11101 *
1$
19
13
1-
1'
#310
0$
09
03
0-
0'
#315
b11110 B
b11111 ?
b11110 ;
b11110 @
b11110 #
b11110 *
1$
19
13
1-
1'
#320
0$
09
03
0-
0'
#325
b11111 B
b100000 ?
b11111 ;
b11111 @
b11111 #
b11111 *
1$
19
13
1-
1'
#330
0$
09
03
0-
0'
#335
b100000 B
b100001 ?
b100000 ;
b100000 @
b100000 #
b100000 *
1$
19
13
1-
1'
#340
0$
09
03
0-
0'
#345
b100001 B
b100010 ?
b100001 ;
b100001 @
b100001 #
b100001 *
1$
19
13
1-
1'
#350
0$
09
03
0-
0'
#355
b100010 B
b100011 ?
b100010 ;
b100010 @
b100010 #
b100010 *
1$
19
13
1-
1'
#360
0$
09
03
0-
0'
#365
b100011 B
b100100 ?
b100011 ;
b100011 @
b100011 #
b100011 *
1$
19
13
1-
1'
#370
0$
09
03
0-
0'
#375
b100100 B
b100101 ?
b100100 ;
b100100 @
b100100 #
b100100 *
1$
19
13
1-
1'
#380
0$
09
03
0-
0'
#385
b100101 B
b100110 ?
b100101 ;
b100101 @
b100101 #
b100101 *
1$
19
13
1-
1'
#390
0$
09
03
0-
0'
#395
b100110 B
b100111 ?
b100110 ;
b100110 @
b100110 #
b100110 *
1$
19
13
1-
1'
#400
0$
09
03
0-
0'
#405
b100111 B
b101000 ?
b100111 ;
b100111 @
b100111 #
b100111 *
1$
19
13
1-
1'
#410
0$
09
03
0-
0'
#415
b101000 B
b101001 ?
b101000 ;
b101000 @
b101000 #
b101000 *
1$
19
13
1-
1'
#420
0$
09
03
0-
0'
#425
b101001 B
b101010 ?
b101001 ;
b101001 @
b101001 #
b101001 *
1$
19
13
1-
1'
#430
0$
09
03
0-
0'
#435
b101010 B
b101011 ?
b101010 ;
b101010 @
b101010 #
b101010 *
1$
19
13
1-
1'
#440
0$
09
03
0-
0'
#445
b101011 B
b101100 ?
b101011 ;
b101011 @
b101011 #
b101011 *
1$
19
13
1-
1'
#450
0$
09
03
0-
0'
#455
b101100 B
b101101 ?
b101100 ;
b101100 @
b101100 #
b101100 *
1$
19
13
1-
1'
#460
0$
09
03
0-
0'
#465
b101101 B
b101110 ?
b101101 ;
b101101 @
b101101 #
b101101 *
1$
19
13
1-
1'
#470
0$
09
03
0-
0'
#475
b101110 B
b101111 ?
b101110 ;
b101110 @
b101110 #
b101110 *
1$
19
13
1-
1'
#480
0$
09
03
0-
0'
#485
b101111 B
b110000 ?
b101111 ;
b101111 @
b101111 #
b101111 *
1$
19
13
1-
1'
#490
0$
09
03
0-
0'
#495
b110000 B
b110001 ?
b110000 ;
b110000 @
b110000 #
b110000 *
1$
19
13
1-
1'
#500
0$
09
03
0-
0'
#505
b110001 B
b110010 ?
b110001 ;
b110001 @
b110001 #
b110001 *
1$
19
13
1-
1'
#510
0$
09
03
0-
0'
#515
b110010 B
b110011 ?
b110010 ;
b110010 @
b110010 #
b110010 *
1$
19
13
1-
1'
#520
0$
09
03
0-
0'
#525
b110011 B
b110100 ?
b110011 ;
b110011 @
b110011 #
b110011 *
1$
19
13
1-
1'
#530
0$
09
03
0-
0'
#535
b110100 B
b110101 ?
b110100 ;
b110100 @
b110100 #
b110100 *
1$
19
13
1-
1'
#540
0$
09
03
0-
0'
#545
b110101 B
b110110 ?
b110101 ;
b110101 @
b110101 #
b110101 *
1$
19
13
1-
1'
#550
0$
09
03
0-
0'
#555
b110110 B
b110111 ?
b110110 ;
b110110 @
b110110 #
b110110 *
1$
19
13
1-
1'
#560
0$
09
03
0-
0'
#565
b110111 B
b111000 ?
b110111 ;
b110111 @
b110111 #
b110111 *
1$
19
13
1-
1'
#570
0$
09
03
0-
0'
#575
b111000 B
b111001 ?
b111000 ;
b111000 @
b111000 #
b111000 *
1$
19
13
1-
1'
#580
0$
09
03
0-
0'
#585
b111001 B
b111010 ?
b111001 ;
b111001 @
b111001 #
b111001 *
1$
19
13
1-
1'
#590
0$
09
03
0-
0'
#595
b111010 B
b111011 ?
b111010 ;
b111010 @
b111010 #
b111010 *
1$
19
13
1-
1'
#600
0$
09
03
0-
0'
#605
1:
17
b111011 B
b111100 ?
b111011 ;
b111011 @
b111011 #
b111011 *
1$
19
13
1-
1'
#610
0$
09
03
0-
0'
#615
0:
07
b0 B
b1 ?
b0 ;
b0 @
b0 #
b0 *
b1 F
b10 C
b1 5
b1 D
b1 "
b1 )
1$
19
13
1-
1'
#620
0$
09
03
0-
0'
#625
b1 B
b10 ?
b1 ;
b1 @
b1 #
b1 *
1$
19
13
1-
1'
#630
0$
09
03
0-
0'
#635
b10 B
b11 ?
b10 ;
b10 @
b10 #
b10 *
1$
19
13
1-
1'
#640
0$
09
03
0-
0'
#645
b11 B
b100 ?
b11 ;
b11 @
b11 #
b11 *
1$
19
13
1-
1'
#650
0$
09
03
0-
0'
#655
b100 B
b101 ?
b100 ;
b100 @
b100 #
b100 *
1$
19
13
1-
1'
#660
0$
09
03
0-
0'
#665
b101 B
b110 ?
b101 ;
b101 @
b101 #
b101 *
1$
19
13
1-
1'
#670
0$
09
03
0-
0'
#675
b110 B
b111 ?
b110 ;
b110 @
b110 #
b110 *
1$
19
13
1-
1'
#680
0$
09
03
0-
0'
#685
b111 B
b1000 ?
b111 ;
b111 @
b111 #
b111 *
1$
19
13
1-
1'
#690
0$
09
03
0-
0'
#695
b1000 B
b1001 ?
b1000 ;
b1000 @
b1000 #
b1000 *
1$
19
13
1-
1'
#700
0$
09
03
0-
0'
#705
b1001 B
b1010 ?
b1001 ;
b1001 @
b1001 #
b1001 *
1$
19
13
1-
1'
#710
0$
09
03
0-
0'
#715
b1010 B
b1011 ?
b1010 ;
b1010 @
b1010 #
b1010 *
1$
19
13
1-
1'
#720
0$
09
03
0-
0'
#725
b1011 B
b1100 ?
b1011 ;
b1011 @
b1011 #
b1011 *
1$
19
13
1-
1'
#730
0$
09
03
0-
0'
#735
b1100 B
b1101 ?
b1100 ;
b1100 @
b1100 #
b1100 *
1$
19
13
1-
1'
#740
0$
09
03
0-
0'
#745
b1101 B
b1110 ?
b1101 ;
b1101 @
b1101 #
b1101 *
1$
19
13
1-
1'
#750
0$
09
03
0-
0'
#755
b1110 B
b1111 ?
b1110 ;
b1110 @
b1110 #
b1110 *
1$
19
13
1-
1'
#760
0$
09
03
0-
0'
#765
b1111 B
b10000 ?
b1111 ;
b1111 @
b1111 #
b1111 *
1$
19
13
1-
1'
#770
0$
09
03
0-
0'
#775
b10000 B
b10001 ?
b10000 ;
b10000 @
b10000 #
b10000 *
1$
19
13
1-
1'
#780
0$
09
03
0-
0'
#785
b10001 B
b10010 ?
b10001 ;
b10001 @
b10001 #
b10001 *
1$
19
13
1-
1'
#790
0$
09
03
0-
0'
#795
b10010 B
b10011 ?
b10010 ;
b10010 @
b10010 #
b10010 *
1$
19
13
1-
1'
#800
0$
09
03
0-
0'
#805
b10011 B
b10100 ?
b10011 ;
b10011 @
b10011 #
b10011 *
1$
19
13
1-
1'
#810
0$
09
03
0-
0'
#815
b10100 B
b10101 ?
b10100 ;
b10100 @
b10100 #
b10100 *
1$
19
13
1-
1'
#820
0$
09
03
0-
0'
#825
b10101 B
b10110 ?
b10101 ;
b10101 @
b10101 #
b10101 *
1$
19
13
1-
1'
#830
0$
09
03
0-
0'
#835
b10110 B
b10111 ?
b10110 ;
b10110 @
b10110 #
b10110 *
1$
19
13
1-
1'
#840
0$
09
03
0-
0'
#845
b10111 B
b11000 ?
b10111 ;
b10111 @
b10111 #
b10111 *
1$
19
13
1-
1'
#850
0$
09
03
0-
0'
#855
b11000 B
b11001 ?
b11000 ;
b11000 @
b11000 #
b11000 *
1$
19
13
1-
1'
#860
0$
09
03
0-
0'
#865
b11001 B
b11010 ?
b11001 ;
b11001 @
b11001 #
b11001 *
1$
19
13
1-
1'
#870
0$
09
03
0-
0'
#875
b11010 B
b11011 ?
b11010 ;
b11010 @
b11010 #
b11010 *
1$
19
13
1-
1'
#880
0$
09
03
0-
0'
#885
b11011 B
b11100 ?
b11011 ;
b11011 @
b11011 #
b11011 *
1$
19
13
1-
1'
#890
0$
09
03
0-
0'
#895
b11100 B
b11101 ?
b11100 ;
b11100 @
b11100 #
b11100 *
1$
19
13
1-
1'
#900
0$
09
03
0-
0'
#905
b11101 B
b11110 ?
b11101 ;
b11101 @
b11101 #
b11101 *
1$
19
13
1-
1'
#910
0$
09
03
0-
0'
#915
b11110 B
b11111 ?
b11110 ;
b11110 @
b11110 #
b11110 *
1$
19
13
1-
1'
#920
0$
09
03
0-
0'
#925
b11111 B
b100000 ?
b11111 ;
b11111 @
b11111 #
b11111 *
1$
19
13
1-
1'
#930
0$
09
03
0-
0'
#935
b100000 B
b100001 ?
b100000 ;
b100000 @
b100000 #
b100000 *
1$
19
13
1-
1'
#940
0$
09
03
0-
0'
#945
b100001 B
b100010 ?
b100001 ;
b100001 @
b100001 #
b100001 *
1$
19
13
1-
1'
#950
0$
09
03
0-
0'
#955
b100010 B
b100011 ?
b100010 ;
b100010 @
b100010 #
b100010 *
1$
19
13
1-
1'
#960
0$
09
03
0-
0'
#965
b100011 B
b100100 ?
b100011 ;
b100011 @
b100011 #
b100011 *
1$
19
13
1-
1'
#970
0$
09
03
0-
0'
#975
b100100 B
b100101 ?
b100100 ;
b100100 @
b100100 #
b100100 *
1$
19
13
1-
1'
#980
0$
09
03
0-
0'
#985
b100101 B
b100110 ?
b100101 ;
b100101 @
b100101 #
b100101 *
1$
19
13
1-
1'
#990
0$
09
03
0-
0'
#995
b100110 B
b100111 ?
b100110 ;
b100110 @
b100110 #
b100110 *
1$
19
13
1-
1'
#1000
0$
09
03
0-
0'
#1005
b100111 B
b101000 ?
b100111 ;
b100111 @
b100111 #
b100111 *
1$
19
13
1-
1'
#1010
0$
09
03
0-
0'
#1015
b101000 B
b101001 ?
b101000 ;
b101000 @
b101000 #
b101000 *
1$
19
13
1-
1'
#1020
0$
09
03
0-
0'
#1025
b101001 B
b101010 ?
b101001 ;
b101001 @
b101001 #
b101001 *
1$
19
13
1-
1'
#1030
0$
09
03
0-
0'
#1035
b101010 B
b101011 ?
b101010 ;
b101010 @
b101010 #
b101010 *
1$
19
13
1-
1'
#1040
0$
09
03
0-
0'
#1045
b101011 B
b101100 ?
b101011 ;
b101011 @
b101011 #
b101011 *
1$
19
13
1-
1'
#1050
0$
09
03
0-
0'
#1055
b101100 B
b101101 ?
b101100 ;
b101100 @
b101100 #
b101100 *
1$
19
13
1-
1'
#1060
0$
09
03
0-
0'
#1065
b101101 B
b101110 ?
b101101 ;
b101101 @
b101101 #
b101101 *
1$
19
13
1-
1'
#1070
0$
09
03
0-
0'
#1075
b101110 B
b101111 ?
b101110 ;
b101110 @
b101110 #
b101110 *
1$
19
13
1-
1'
#1080
0$
09
03
0-
0'
#1085
b101111 B
b110000 ?
b101111 ;
b101111 @
b101111 #
b101111 *
1$
19
13
1-
1'
#1090
0$
09
03
0-
0'
#1095
b110000 B
b110001 ?
b110000 ;
b110000 @
b110000 #
b110000 *
1$
19
13
1-
1'
#1100
0$
09
03
0-
0'
#1105
b110001 B
b110010 ?
b110001 ;
b110001 @
b110001 #
b110001 *
1$
19
13
1-
1'
#1110
0$
09
03
0-
0'
#1115
b110010 B
b110011 ?
b110010 ;
b110010 @
b110010 #
b110010 *
1$
19
13
1-
1'
#1120
0$
09
03
0-
0'
#1125
b110011 B
b110100 ?
b110011 ;
b110011 @
b110011 #
b110011 *
1$
19
13
1-
1'
#1130
0$
09
03
0-
0'
#1135
b110100 B
b110101 ?
b110100 ;
b110100 @
b110100 #
b110100 *
1$
19
13
1-
1'
#1140
0$
09
03
0-
0'
#1145
b110101 B
b110110 ?
b110101 ;
b110101 @
b110101 #
b110101 *
1$
19
13
1-
1'
#1150
0$
09
03
0-
0'
#1155
b110110 B
b110111 ?
b110110 ;
b110110 @
b110110 #
b110110 *
1$
19
13
1-
1'
#1160
0$
09
03
0-
0'
#1165
b110111 B
b111000 ?
b110111 ;
b110111 @
b110111 #
b110111 *
1$
19
13
1-
1'
#1170
0$
09
03
0-
0'
#1175
b111000 B
b111001 ?
b111000 ;
b111000 @
b111000 #
b111000 *
1$
19
13
1-
1'
#1180
0$
09
03
0-
0'
#1185
b111001 B
b111010 ?
b111001 ;
b111001 @
b111001 #
b111001 *
1$
19
13
1-
1'
#1190
0$
09
03
0-
0'
#1195
b111010 B
b111011 ?
b111010 ;
b111010 @
b111010 #
b111010 *
1$
19
13
1-
1'
#1200
0$
09
03
0-
0'
#1205
1:
17
b111011 B
b111100 ?
b111011 ;
b111011 @
b111011 #
b111011 *
1$
19
13
1-
1'
#1210
0$
09
03
0-
0'
#1215
0:
07
b0 B
b1 ?
b0 ;
b0 @
b0 #
b0 *
b10 F
b11 C
b10 5
b10 D
b10 "
b10 )
1$
19
13
1-
1'
#1220
0$
09
03
0-
0'
#1225
b1 B
b10 ?
b1 ;
b1 @
b1 #
b1 *
1$
19
13
1-
1'
#1230
0$
09
03
0-
0'
#1235
b10 B
b11 ?
b10 ;
b10 @
b10 #
b10 *
1$
19
13
1-
1'
#1240
0$
09
03
0-
0'
#1245
b11 B
b100 ?
b11 ;
b11 @
b11 #
b11 *
1$
19
13
1-
1'
#1250
0$
09
03
0-
0'
#1255
b100 B
b101 ?
b100 ;
b100 @
b100 #
b100 *
1$
19
13
1-
1'
#1260
0$
09
03
0-
0'
#1265
b101 B
b110 ?
b101 ;
b101 @
b101 #
b101 *
1$
19
13
1-
1'
#1270
0$
09
03
0-
0'
#1275
b110 B
b111 ?
b110 ;
b110 @
b110 #
b110 *
1$
19
13
1-
1'
#1280
0$
09
03
0-
0'
#1285
b111 B
b1000 ?
b111 ;
b111 @
b111 #
b111 *
1$
19
13
1-
1'
#1290
0$
09
03
0-
0'
#1295
b1000 B
b1001 ?
b1000 ;
b1000 @
b1000 #
b1000 *
1$
19
13
1-
1'
#1300
0$
09
03
0-
0'
#1305
b1001 B
b1010 ?
b1001 ;
b1001 @
b1001 #
b1001 *
1$
19
13
1-
1'
#1310
0$
09
03
0-
0'
#1315
b1010 B
b1011 ?
b1010 ;
b1010 @
b1010 #
b1010 *
1$
19
13
1-
1'
#1320
0$
09
03
0-
0'
#1325
b1011 B
b1100 ?
b1011 ;
b1011 @
b1011 #
b1011 *
1$
19
13
1-
1'
#1330
0$
09
03
0-
0'
#1335
b1100 B
b1101 ?
b1100 ;
b1100 @
b1100 #
b1100 *
1$
19
13
1-
1'
#1340
0$
09
03
0-
0'
#1345
b1101 B
b1110 ?
b1101 ;
b1101 @
b1101 #
b1101 *
1$
19
13
1-
1'
#1350
0$
09
03
0-
0'
#1355
b1110 B
b1111 ?
b1110 ;
b1110 @
b1110 #
b1110 *
1$
19
13
1-
1'
#1360
0$
09
03
0-
0'
#1365
b1111 B
b10000 ?
b1111 ;
b1111 @
b1111 #
b1111 *
1$
19
13
1-
1'
#1370
0$
09
03
0-
0'
#1375
b10000 B
b10001 ?
b10000 ;
b10000 @
b10000 #
b10000 *
1$
19
13
1-
1'
#1380
0$
09
03
0-
0'
#1385
b10001 B
b10010 ?
b10001 ;
b10001 @
b10001 #
b10001 *
1$
19
13
1-
1'
#1390
0$
09
03
0-
0'
#1395
b10010 B
b10011 ?
b10010 ;
b10010 @
b10010 #
b10010 *
1$
19
13
1-
1'
#1400
0$
09
03
0-
0'
#1405
b10011 B
b10100 ?
b10011 ;
b10011 @
b10011 #
b10011 *
1$
19
13
1-
1'
#1410
0$
09
03
0-
0'
#1415
b10100 B
b10101 ?
b10100 ;
b10100 @
b10100 #
b10100 *
1$
19
13
1-
1'
#1420
0$
09
03
0-
0'
#1425
b10101 B
b10110 ?
b10101 ;
b10101 @
b10101 #
b10101 *
1$
19
13
1-
1'
#1430
0$
09
03
0-
0'
#1435
b10110 B
b10111 ?
b10110 ;
b10110 @
b10110 #
b10110 *
1$
19
13
1-
1'
#1440
0$
09
03
0-
0'
#1445
b10111 B
b11000 ?
b10111 ;
b10111 @
b10111 #
b10111 *
1$
19
13
1-
1'
#1450
0$
09
03
0-
0'
#1455
b11000 B
b11001 ?
b11000 ;
b11000 @
b11000 #
b11000 *
1$
19
13
1-
1'
#1460
0$
09
03
0-
0'
#1465
b11001 B
b11010 ?
b11001 ;
b11001 @
b11001 #
b11001 *
1$
19
13
1-
1'
#1470
0$
09
03
0-
0'
#1475
b11010 B
b11011 ?
b11010 ;
b11010 @
b11010 #
b11010 *
1$
19
13
1-
1'
#1480
0$
09
03
0-
0'
#1485
b11011 B
b11100 ?
b11011 ;
b11011 @
b11011 #
b11011 *
1$
19
13
1-
1'
#1490
0$
09
03
0-
0'
#1495
b11100 B
b11101 ?
b11100 ;
b11100 @
b11100 #
b11100 *
1$
19
13
1-
1'
#1500
0$
09
03
0-
0'
#1505
b11101 B
b11110 ?
b11101 ;
b11101 @
b11101 #
b11101 *
1$
19
13
1-
1'
#1510
0$
09
03
0-
0'
#1515
b11110 B
b11111 ?
b11110 ;
b11110 @
b11110 #
b11110 *
1$
19
13
1-
1'
#1520
0$
09
03
0-
0'
#1525
b11111 B
b100000 ?
b11111 ;
b11111 @
b11111 #
b11111 *
1$
19
13
1-
1'
